httpgogui-0.2.0.dist-info/METADATA
httpgogui-0.2.0.dist-info/WHEEL
httpgogui-0.2.0.dist-info/entry_points.txt
httpgogui/cache/sqlite_db.py
httpgogui/components/table_widget.py
httpgogui/layout/body.py
httpgogui/layout/bottom.py
httpgogui/layout/header.py
httpgogui/main.py
httpgogui/thread/request_thread.py
httpgogui/utils/enum/error.py
httpgogui/utils/header_list.py
httpgogui-0.2.0.dist-info/RECORD
